[
  {
    "id": "Part 29 – The Multi-track",
    "content": "PART 29 - THE MULTI-TRACK\n\n---\n\nContents of this Part\n\n---\n\nScope of this Part\n\n29.1 This Part contains general provisions about management of cases allocated to the multi-track and applies only to cases allocated to that track.\n\n(Part 27 sets out the procedure for claims allocated to the small claims track)\n\n(Part 28 sets out the procedure for claims allocated to the fast track or intermediate track)\n\n(2) When drafting case management directions both the parties and the court should take as their starting point any relevant model directions and standard directions which can be found online atwww.justice.gov.uk/courts/procedure-rules/civiland adapt them as appropriate to the circumstances of the particular case.\n\n---\n\nCase management\n\n29.2\n\n(1) When it allocates a case to the multi-track, the court will -\n\n(a) give directions for the management of the case and set a timetable for the steps to be taken between the giving of directions and the trial; ormay\n\n(b) fix -\n\n(i) a case management conference; or\n\n(ii) a pre-trial review,\n\nor both, and give such other directions relating to the management of the case as it sees fit.\n\n(1 A) When giving directions, the court must consider whether to order or encourage the parties to engage in alternative dispute resolution.\n\n(2) The court will fix the trial date or the period in which the trial is to take place as soon as practicable.\n\n(3) When the court fixes the trial date or the trial period under paragraph (2), it will -\n\n(a) give notice to the parties of the date or period; and\n\n(b) specify the date by which the parties must file a pre-trial check list.\n\n---\n\nCase management conference and pre-trial review\n\n29.3\n\n(1) The court may fix -\n\n(a) a case management conference; or\n\n(b) a pre-trial review, at any time after the claim has been allocated.\n\n(2) If a party has a legal representative, a representative -\n\n(a) familiar with the case; and\n\n(b) with sufficient authority to deal with any issues that are likely to arise, must attend case management conferences and pre-trial reviews.\n\n(Rule 3.1(2)(c) provides that the court may require a party to attend the court)\n\n---\n\nSteps taken by the parties\n\n29.4 The parties must endeavour to agree appropriate directions for the management of the proceedings and submit agreed directions, or their respective proposals to the court at least seven days before any case management conference. Where the court approves agreed directions, or issues its own directions, the parties will be so notified by the court and the case management conference will be vacated.\n\n---\n\nVariation of case management timetable\n\n29.5\n\n(1) A party must apply to the court if he wishes to vary the date which the court has fixed for -\n\n(a) a case management conference;\n\n(b) a pre-trial review;\n\n(c) the return of a pre-trial check list under rule 29.6;\n\n(d) the trial; or\n\n(e) the trial period.\n\n(2) Any date set by the court or these Rules for doing any act may not be varied by the parties if the variation would make it necessary to vary any of the dates mentioned in paragraph (1).\n\n(Rule 2.11 allows the parties to vary a date by written agreement except where the rules provide otherwise or the court orders otherwise)\n\n---\n\nPre-trial check list (listing questionnaire)\n\n29.6\n\n(1) The court will send the parties a pre-trial check list (listing questionnaire) for completion and return by the date specified in directions given under rule 29.2(3) unless it considers that the claim can proceed to trial without the need for a pre-trial check list.\n\n(2) Each party must file the completed pre-trial check list by the date specified by the court.\n\n(3) If no party files the completed pre-trial checklist by the date specified, the court will order that unless a completed pre-trial checklist is filed within 7 days from service of that order, the claim, defence and any counterclaim will be struck out without further order of the court.\n\n(4) If -\n\n(a) a party files a completed pre-trial checklist but another party does not;\n\n(b) a party has failed to give all the information requested by the pre-trial checklist; or\n\n(c) the court considers that a hearing is necessary to enable it to decide what directions to give in order to complete preparation of the case for trial,\n\nthe court may give such directions as it thinks appropriate.\n\n---\n\nPre-trial review\n\n29.7 If, on receipt of the parties' pre-trial check lists, the court decides -\n\n(a) to hold a pre-trial review; or\n\n(b) to cancel a pre-trial review which has already been fixed,\n\nit will serve notice of its decision at least 7 days before the date fixed for the hearing or, as the case may be, the cancelled hearing.\n\n---\n\nSetting a trial timetable and confirming the trial date or week\n\n29.8 As soon as practicable after -\n\n(a) each party has filed a completed pre-trial check list;\n\n(b) the court has held a listing hearing under rule 29.6(3); or\n\n(c) the court has held a pre-trial review under rule 29.7,\n\nthe court will -\n\n(i) set a timetable for the trial unless a timetable has already been fixed, or the court considers that it would be inappropriate to do so;\n\n(ii) confirm the date for trial or the week within which the trial is to begin; and\n\n(iii) notify the parties of the trial timetable (where one is fixed under this rule) and the date or trial period.\n\n---\n\nConduct of trial\n\n29.9 Unless the trial judge otherwise directs, the trial will be conducted in accordance with any order previously made.",
    "category": "Civil Procedure Rules and Practice Directions",
    "sourcepage": "The Multi-track",
    "sourcefile": "Part 29",
    "storageUrl": "https://www.justice.gov.uk/courts/procedure-rules/civil/rules/part29",
    "oids": [],
    "groups": [],
    "parent_id": "Part 29 – The Multi-track",
    "embedding": [
      0.040621042251586914,
      0.0009022658341564238,
      -0.012753637507557869,
      0.02778550796210766,
      -0.014480925165116787,
      0.027636602520942688,
      -0.022439850494265556,
      0.053277891129255295,
      0.008011041209101677,
      -0.015203109942376614,
      0.021516643464565277,
      0.04413517937064171,
      -0.014763842336833477,
      -0.05557101592421532,
      -0.030614685267210007,
      -0.006797472946345806,
      -0.005788647569715977,
      0.01272385660558939,
      0.011309267021715641,
      0.022424958646297455,
      0.026698507368564606,
      0.05140170082449913,
      -0.004843106027692556,
      0.03296737000346184,
      0.024152247235178947,
      0.016334781423211098,
      -0.0003887793282046914,
      -0.005453613121062517,
      -0.02708565816283226,
      0.003698405809700489,
      -0.04321197420358658,
      0.02657938376069069,
      0.002916659228503704,
      -0.01834498718380928,
      -0.0031772414222359657,
      -0.0020790735725313425,
      0.03514137119054794,
      -0.017451561987400055,
      -0.021010370925068855,
      -0.0156349316239357,
      -0.0008315364248119295,
      -0.012336705811321735,
      -0.02510523423552513,
      0.0016854084096848965,
      -0.019670233130455017,
      0.024479836225509644,
      -0.017168644815683365,
      0.0058147055096924305,
      0.016245437785983086,
      -0.01676660217344761,
      0.025507275015115738,
      -0.013364143669605255,
      0.009946794249117374,
      -0.026698507368564606,
      0.005207921378314495,
      -0.020280739292502403,
      0.007765349466353655,
      0.036779314279556274,
      -0.0016565582482144237,
      -0.01148050744086504,
      0.00988723337650299,
      0.005319599527865648,
      -0.006510832346975803,
      -0.002670967485755682,
      -0.0033131164964288473,
      0.014875520952045918,
      0.025075452402234077,
      -0.012962102890014648,
      -0.030435999855399132,
      -0.026817630976438522,
      0.0005039473762735724,
      -0.03085293248295784,
      0.007668561767786741,
      -0.0007594109629280865,
      0.009619205258786678,
      -0.033443864434957504,
      0.023705534636974335,
      0.03505202755331993,
      -0.00650338688865304,
      -0.020206287503242493,
      0.0209805890917778,
      -0.009626651182770729,
      -0.020161617547273636,
      0.04818537086248398,
      -0.001148422947153449,
      -0.018374767154455185,
      -0.024271370843052864,
      -0.06563693284988403,
      0.04294394701719284,
      -0.03249087557196617,
      0.018672576174139977,
      -0.00892680138349533,
      0.05432021990418434,
      0.04208030179142952,
      0.039072439074516296,
      0.003402458969503641,
      0.032222848385572433,
      0.009254390373826027,
      -0.0220378078520298,
      -0.071116603910923,
      0.01457026693969965,
      0.00959687028080225,
      -0.003979462198913097,
      -0.03240153566002846,
      -0.009842561557888985,
      -0.019536219537258148,
      0.015620041638612747,
      -0.005825873464345932,
      0.0220378078520298,
      0.03290781006217003,
      0.000369468325516209,
      -0.02190379425883293,
      -0.014131000265479088,
      -0.03353320434689522,
      -0.02005738392472267,
      -0.0469047948718071,
      -0.039638273417949677,
      -0.06313534080982208,
      0.06432657688856125,
      -0.058757562190294266,
      -0.037851426750421524,
      -0.05571991950273514,
      0.004519239999353886,
      -0.0031325703021138906,
      -0.03654107078909874,
      0.027830177918076515,
      -0.0059747775085270405,
      0.025462603196501732,
      0.019729794934391975,
      -0.004686756990849972,
      -0.022916343063116074,
      -0.0015588399255648255,
      -0.016677260398864746,
      -0.00744892843067646,
      -0.02957235649228096,
      0.020072273910045624,
      0.009105486795306206,
      -0.033146053552627563,
      -0.013490712270140648,
      0.006469883490353823,
      -0.02083168551325798,
      -0.03582632914185524,
      0.02657938376069069,
      -0.019655343145132065,
      0.007099003531038761,
      0.018881041556596756,
      0.012239918112754822,
      0.01481595914810896,
      -0.007013383787125349,
      -0.004482013639062643,
      -0.025685958564281464,
      -0.02260364405810833,
      -0.0231099184602499,
      0.016945287585258484,
      -0.0195511095225811,
      0.0006421490106731653,
      -0.009418184868991375,
      -0.011994225904345512,
      -0.015724273398518562,
      -0.001166105386801064,
      0.03823857754468918,
      0.024911658838391304,
      -0.004299606196582317,
      0.010691314935684204,
      0.027666384354233742,
      0.03121030144393444,
      0.00970110297203064,
      -0.02410757541656494,
      -0.03865550830960274,
      0.01634967140853405,
      -0.017287766560912132,
      0.019491547718644142,
      0.006064119748771191,
      -0.050508275628089905,
      -0.017034631222486496,
      0.010155260562896729,
      0.02787484973669052,
      0.03919156268239021,
      -0.004180483054369688,
      0.005062739830464125,
      -0.01975957490503788,
      0.019506439566612244,
      -0.001355027430690825,
      -0.03442662954330444,
      -0.01998293213546276,
      0.004943616688251495,
      0.02991483546793461,
      -0.018091849982738495,
      -0.007061777636408806,
      0.036570850759744644,
      -0.028321562334895134,
      0.009135267697274685,
      0.048155590891838074,
      -0.0011437697103247046,
      0.004292161203920841,
      -0.01821097359061241,
      -0.014912746846675873,
      0.00712878443300724,
      -0.02680274099111557,
      0.033086493611335754,
      0.03100183606147766,
      0.016260329633951187,
      0.006507109850645065,
      0.03320561721920967,
      -0.009678767062723637,
      0.0035457792691886425,
      0.004284715745598078,
      0.01168897282332182,
      0.014056548476219177,
      -0.051639944314956665,
      0.0016491130227223039,
      -0.005874267313629389,
      0.025045672431588173,
      0.00023964255524333566,
      -0.010534966364502907,
      0.012202692218124866,
      0.006659736391156912,
      0.03773230314254761,
      0.03680909797549248,
      -0.03100183606147766,
      0.01155495923012495,
      -0.028738493099808693,
      0.0003240991209167987,
      -0.015620041638612747,
      -0.039906300604343414,
      0.01996804215013981,
      -0.007608999963849783,
      0.028202438727021217,
      0.030614685267210007,
      0.005889157764613628,
      -0.0016677260864526033,
      0.008465198799967766,
      -0.027353685349225998,
      -0.007988705299794674,
      0.040769945830106735,
      -0.03278868645429611,
      0.0066225104965269566,
      -0.014696835540235043,
      0.019253302365541458,
      0.003033921355381608,
      0.020921027287840843,
      0.017808930948376656,
      -0.03448619320988655,
      0.03389057517051697,
      0.0051111336797475815,
      0.04493926092982292,
      -0.026772959157824516,
      0.07165265828371048,
      0.021069932729005814,
      -0.02431604079902172,
      0.015590260736644268,
      0.051580384373664856,
      -0.009425629861652851,
      0.011361383832991123,
      0.02096569910645485,
      0.0060529522597789764,
      -0.008286513388156891,
      0.0006114374846220016,
      -0.0016816857969388366,
      -0.005375438369810581,
      0.0010479126358404756,
      0.05345657467842102,
      -0.0020325412042438984,
      0.017540903761982918,
      0.0319846048951149,
      -0.02567106857895851,
      0.020295631140470505,
      -0.0469047948718071,
      0.021069932729005814,
      -0.027383465319871902,
      0.0280833151191473,
      0.007225572131574154,
      -0.015232890844345093,
      0.00572536326944828,
      0.00938095897436142,
      -0.024182027205824852,
      0.017034631222486496,
      -0.03558808192610741,
      -0.01740689016878605,
      0.014302239753305912,
      -0.008279068395495415,
      0.0003671417071018368,
      -0.02906608209013939,
      0.025209465995430946,
      -0.04106775298714638,
      -0.010400951839983463,
      -0.018359877169132233,
      -0.027740836143493652,
      -0.018017398193478584,
      0.003422933164983988,
      -0.025537054985761642,
      -0.00832374021410942,
      -0.005312154069542885,
      -0.02928943932056427,
      0.016513466835021973,
      -0.04249723255634308,
      0.00416187010705471,
      0.019863808527588844,
      0.015262671746313572,
      -0.013073781505227089,
      -0.007661116775125265,
      0.043390657752752304,
      0.036868657916784286,
      0.02267809584736824,
      0.03716646507382393,
      0.055630575865507126,
      -0.007203236222267151,
      -0.0038026387337595224,
      -0.04422452300786972,
      -0.010899781249463558,
      0.007530825678259134,
      -0.03055512346327305,
      -0.0033373134210705757,
      -0.010951897129416466,
      -0.008115273900330067,
      -0.005770034156739712,
      0.01876191794872284,
      0.04038279503583908,
      -0.03889375552535057,
      -0.03439684957265854,
      -0.00019171404710505158,
      -0.002667244989424944,
      -0.04970419406890869,
      -0.021710218861699104,
      -0.007430315017700195,
      -0.05539232864975929,
      0.019387315958738327,
      0.017540903761982918,
      -0.05601772665977478,
      -0.0024829760659486055,
      -0.012589843012392521,
      -0.018568342551589012,
      0.023199260234832764,
      -0.039906300604343414,
      -0.036719754338264465,
      -0.014413918368518353,
      -0.03374167159199715,
      -0.01891082152724266,
      0.01148050744086504,
      0.008092938922345638,
      0.003422933164983988,
      -0.006529445294290781,
      0.03755361586809158,
      0.005743976216763258,
      0.010244603268802166,
      0.01629010960459709,
      0.019938260316848755,
      -0.025343479588627815,
      0.04556465893983841,
      -0.003201438346877694,
      0.0008250218234024942,
      0.010862555354833603,
      -0.019565999507904053,
      0.01664748042821884,
      0.0030506730545312166,
      -0.004359168000519276,
      -0.01996804215013981,
      -0.021844232454895973,
      0.020295631140470505,
      -0.02908097393810749,
      0.05208665877580643,
      -0.03654107078909874,
      0.02209736965596676,
      -0.0037561061326414347,
      0.002060460625216365,
      0.026683617383241653,
      0.010036136955022812,
      0.023839548230171204,
      -0.00442617479711771,
      -0.011607075110077858,
      -0.0026169896591454744,
      0.029393671080470085,
      0.0703423023223877,
      0.010103143751621246,
      0.029483014717698097,
      0.002469946863129735,
      0.03392035514116287,
      -0.014868075959384441,
      -0.020787013694643974,
      0.001805462408810854,
      0.009142712689936161,
      0.01777915097773075,
      0.020712561905384064,
      0.0011549375485628843,
      -0.010557301342487335,
      0.004139534197747707,
      0.03588589280843735,
      0.00588543526828289,
      -0.007489876821637154,
      -0.0016230548499152064,
      -0.01862790435552597,
      0.04770887643098831,
      0.003953404258936644,
      0.005695582367479801,
      -0.012768527492880821,
      -0.02751748077571392,
      0.009179938584566116,
      -0.004240044392645359,
      0.02373531460762024,
      0.013051445595920086,
      0.01030416414141655,
      -0.01468194555491209,
      0.013371589593589306,
      -0.011353938840329647,
      0.011138027533888817,
      -0.006198133807629347,
      0.015977410599589348,
      0.0033801232930272818,
      0.020370082929730415,
      -0.006484773941338062,
      0.014346911571919918,
      -0.012098459526896477,
      -0.007508489768952131,
      -0.05131235718727112,
      0.016885725781321526,
      -0.009440520778298378,
      0.013877863064408302,
      0.06700684875249863,
      -0.020310521125793457,
      -0.021084822714328766,
      0.012433493509888649,
      0.051848411560058594,
      -0.004768654238432646,
      -0.03972761705517769,
      0.042824823409318924,
      0.031448546797037125,
      -0.011212479323148727,
      -0.013066335581243038,
      0.013408815488219261,
      0.018672576174139977,
      0.048304494470357895,
      -0.011495397426187992,
      -0.009872342459857464,
      0.02403312362730503,
      0.010296719148755074,
      0.004187928047031164,
      -0.0014257568400353193,
      -0.009157602675259113,
      -0.006499664392322302,
      0.009008699096739292,
      0.004560188390314579,
      0.03168679401278496,
      0.03716646507382393,
      0.030123302713036537,
      0.001481595914810896,
      -0.0083535211160779,
      -0.0355583019554615,
      0.00340432021766901,
      -0.008092938922345638,
      0.02005738392472267,
      -0.0019618116784840822,
      0.06176542490720749,
      -0.00043484652996994555,
      0.029542576521635056,
      0.04228876903653145,
      0.024137357249855995,
      0.014093774370849133,
      -0.036273043602705,
      -0.020087163895368576,
      -0.03260999917984009,
      -0.013810856267809868,
      0.024718083441257477,
      0.02465852163732052,
      -0.03832791745662689,
      -0.020146725699305534,
      -0.027949301525950432,
      -0.03490312397480011,
      0.05161016434431076,
      0.014748952351510525,
      0.0011586601613089442,
      -0.004254934843629599,
      -0.05869800224900246,
      -0.04315241053700447,
      0.02290145307779312,
      0.015828507021069527,
      -0.003644428215920925,
      0.010371171869337559,
      -0.058608658611774445,
      0.0044671231880784035,
      -0.01634967140853405,
      -0.006123681552708149,
      0.012381376698613167,
      0.014622383750975132,
      0.048364054411649704,
      -0.06242060288786888,
      0.02267809584736824,
      -0.0007519657956436276,
      -0.030331768095493317,
      -0.011063575744628906,
      -0.014592602849006653,
      0.008070603013038635,
      0.033950138837099075,
      0.02175489068031311,
      0.050508275628089905,
      -0.010825328528881073,
      -0.03710690513253212,
      0.01777915097773075,
      -0.010400951839983463,
      0.027636602520942688,
      0.029125643894076347,
      -0.007612722925841808,
      0.032222848385572433,
      -0.023005684837698936,
      0.01591784879565239,
      0.010601973161101341,
      -0.00037947282544337213,
      -0.0009539169841445982,
      -0.04770887643098831,
      -0.016587918624281883,
      -0.025537054985761642,
      0.010661534033715725,
      0.03392035514116287,
      -0.0019953150767832994,
      -0.0018743305699899793,
      0.02972126007080078,
      0.010259493254125118,
      0.0043852259404957294,
      -0.00781746581196785,
      0.0024848373141139746,
      -0.0426461361348629,
      0.010825328528881073,
      0.038506604731082916,
      -0.010430732741951942,
      0.010475404560565948,
      0.009842561557888985,
      -0.0017924332059919834,
      -0.009336288087069988,
      -0.020504096522927284,
      0.003975739702582359,
      -0.03618369996547699,
      -0.01821097359061241,
      0.0004862649948336184,
      0.03666019067168236,
      -0.009552198462188244,
      0.013103561475872993,
      -0.0027714776806533337,
      -0.031448546797037125,
      0.024077795445919037,
      -0.004258657805621624,
      -0.023869330063462257,
      -0.0024438886903226376,
      -0.01232926081866026,
      -0.023199260234832764,
      0.012128239497542381,
      0.027383465319871902,
      0.03100183606147766,
      -0.013460931368172169,
      0.01173364371061325,
      0.003523443592712283,
      0.0003571372071746737,
      -0.010907226242125034,
      0.0083535211160779,
      0.022156931459903717,
      0.018613014370203018,
      0.00034759804839268327,
      -0.012314369902014732,
      0.06048484891653061,
      -0.00821206159889698,
      0.013245020993053913,
      0.01584339700639248,
      -0.01970001496374607,
      -0.005550400819629431,
      0.038566164672374725,
      0.03901287913322449,
      -0.04327153414487839,
      0.026102891191840172,
      -0.003931068349629641,
      0.05038915202021599,
      -0.022484520450234413,
      -0.00917249359190464,
      0.018851259723305702,
      -0.01868746615946293,
      0.011331602931022644,
      -0.03258021920919418,
      0.023765096440911293,
      0.022692985832691193,
      0.019521329551935196,
      -0.02034030109643936,
      -0.018657686188817024,
      0.0038863972295075655,
      0.01311845239251852,
      -0.009127821773290634,
      0.034099042415618896,
      -0.004508072044700384,
      0.00558018172159791,
      -0.014406472444534302,
      0.007735568564385176,
      -0.012649403885006905,
      -0.0191937405616045,
      0.028530027717351913,
      -0.008040822111070156,
      0.004980842582881451,
      0.025462603196501732,
      -0.037285588681697845,
      -0.002254036022350192,
      0.017153752967715263,
      0.006402876693755388,
      -0.03895331546664238,
      0.013900198973715305,
      -0.006656013894826174,
      0.009112931787967682,
      0.027889739722013474,
      -0.005985945463180542,
      -0.014123555272817612,
      -0.03794076666235924,
      0.016587918624281883,
      -0.004738873336464167,
      0.011078465729951859,
      -0.010430732741951942,
      -0.004400116391479969,
      0.007262798026204109,
      -0.009157602675259113,
      -0.02721967175602913,
      0.004318219143897295,
      0.02395867183804512,
      -0.02145708166062832,
      0.001842688419856131,
      -0.003363371593877673,
      -0.009619205258786678,
      -0.01804717816412449,
      0.008502424694597721,
      -0.024494726210832596,
      0.03243131563067436,
      0.003737493185326457,
      0.022439850494265556,
      0.0044075618498027325,
      0.014987198635935783,
      0.010118034668266773,
      -0.005840763915330172,
      0.005598794668912888,
      0.02659427374601364,
      -0.046964358538389206,
      0.014585157856345177,
      -0.03006374090909958,
      0.010051027871668339,
      0.015217999927699566,
      0.025626398622989655,
      -0.00739308912307024,
      -0.002138635376468301,
      -0.004344277549535036,
      -0.0011726198717951775,
      -0.016468795016407967,
      0.03612413629889488,
      0.12758104503154755,
      -0.011309267021715641,
      0.04675589129328728,
      0.007184623274952173,
      0.012262254022061825,
      0.0016667954623699188,
      0.0028775720857083797,
      0.00493989372625947,
      0.03954893350601196,
      0.023511959239840508,
      0.030763588845729828,
      -0.012128239497542381,
      -0.014756397344172001,
      -0.0533374547958374,
      -0.01322268508374691,
      0.03972761705517769,
      -0.021769780665636063,
      -0.0020027603022754192,
      -0.004988287575542927,
      -0.0009366999147459865,
      0.014741507358849049,
      0.035439178347587585,
      -0.01062430813908577,
      -0.006953821983188391,
      0.00920227449387312,
      -0.029587246477603912,
      0.02117416448891163,
      -0.004809602629393339,
      -0.03383101522922516,
      0.00671929819509387,
      0.02893206849694252,
      0.004362890496850014,
      -0.005881712306290865,
      -0.0026858579367399216,
      0.04767909646034241,
      -0.027740836143493652,
      -0.005881712306290865,
      0.002172138774767518,
      -0.04279504343867302,
      -0.010527520440518856,
      0.01783871278166771,
      -0.0016900616465136409,
      0.019565999507904053,
      -0.030019069090485573,
      0.020846575498580933,
      0.008718336001038551,
      -0.03332474082708359,
      -0.021501753479242325,
      0.013833192177116871,
      0.0028142877854406834,
      -0.006522000301629305,
      -0.011666636914014816,
      -0.03311627358198166,
      -0.015679603442549706,
      -0.01062430813908577,
      0.005360547918826342,
      0.022201603278517723,
      -0.0013727097539231181,
      0.011525178328156471,
      -0.006615065038204193,
      -0.033592768013477325,
      0.006015726365149021,
      0.0038901199586689472,
      -0.005583904217928648,
      -0.027919521555304527,
      0.00467558903619647,
      0.010572192259132862,
      0.010043581947684288,
      -0.0302126444876194,
      4.9702564865583554e-05,
      0.022663205862045288,
      0.0038454486057162285,
      0.009753219783306122,
      0.01282808929681778,
      -0.017079301178455353,
      -0.02474786341190338,
      -0.009864897467195988,
      -0.004720260389149189,
      -0.004213986452668905,
      -0.003320561721920967,
      -0.017317548394203186,
      -0.01091467123478651,
      0.009581979364156723,
      0.02991483546793461,
      -0.010512630455195904,
      -0.002581625012680888,
      -0.005941274110227823,
      0.015069096349179745,
      0.011100801639258862,
      0.017183534801006317,
      0.0018743305699899793,
      -0.009850007481873035,
      0.03171657770872116,
      0.014823404140770435,
      -0.015560479834675789,
      -0.0031809641513973475,
      0.0013652645284309983,
      0.0012936044950038195,
      -0.015590260736644268,
      -0.003043227829039097,
      -0.011272041127085686,
      -0.042258985340595245,
      0.020146725699305534,
      0.017317548394203186,
      -0.008204616606235504,
      0.00999146606773138,
      0.0025202021934092045,
      -0.01503187045454979,
      -0.031180521473288536,
      0.017585575580596924,
      -0.03237175568938255,
      -0.018002506345510483,
      0.018925713375210762,
      0.014138445258140564,
      0.025745520368218422,
      0.012909986078739166,
      -0.00792914442718029,
      -0.026549603790044785,
      0.026192232966423035,
      -0.010691314935684204,
      -0.002719361335039139,
      -0.014443699270486832,
      -0.0018510642694309354,
      -0.02424158900976181,
      0.008681110106408596,
      0.024837205186486244,
      0.011190144345164299,
      -0.013639616779983044,
      -0.005126024130731821,
      0.041633591055870056,
      -0.016126316040754318,
      -0.00242527574300766,
      -0.021308178082108498,
      0.015560479834675789,
      -0.011361383832991123,
      0.0060566747561097145,
      0.01205378770828247,
      -0.0017347328830510378,
      0.010899781249463558,
      -0.011316712945699692,
      -0.012225027196109295,
      0.0015513947000727057,
      -0.03859594464302063,
      0.0008366549736820161,
      -0.0017123973229900002,
      -0.003205161076039076,
      0.011971890926361084,
      0.020921027287840843,
      -0.01019993145018816,
      -0.005211643874645233,
      -0.027174999937415123,
      0.02695164456963539,
      0.013520493172109127,
      -0.002131190150976181,
      0.004303328692913055,
      -0.010266938246786594,
      0.01649857498705387,
      0.0022838169243186712,
      -0.01883636973798275,
      -0.021084822714328766,
      0.023720424622297287,
      0.0209805890917778,
      0.023482179269194603,
      -0.02296101488173008,
      -0.002581625012680888,
      0.012664294801652431,
      0.007862136699259281,
      0.004333109594881535,
      0.012664294801652431,
      -0.0014238955918699503,
      -0.0419313982129097,
      0.010065917856991291,
      0.005207921378314495,
      0.0547371506690979,
      -0.00810782890766859,
      0.01364706177264452,
      0.015411575324833393,
      -0.022946123033761978,
      -0.012366486713290215,
      0.034099042415618896,
      -0.01761535555124283,
      -0.004117198754101992,
      0.009663877077400684,
      0.0019357535056769848,
      -0.03015308268368244,
      0.04464145377278328,
      0.014763842336833477,
      0.0003887793282046914,
      0.009663877077400684,
      -0.03791098669171333,
      0.011547514237463474,
      -0.010557301342487335,
      -0.0008222298929467797,
      0.001862232107669115,
      0.03165701404213905,
      -0.01325246598571539,
      0.015195664949715137,
      -0.024152247235178947,
      -0.011272041127085686,
      -0.012120794504880905,
      -0.03356298804283142,
      0.007750459015369415,
      -0.02835134230554104,
      -0.002587208990007639,
      0.04059126228094101,
      -0.012351595796644688,
      0.005747698713093996,
      0.022841891273856163,
      0.018895931541919708,
      0.003041366580873728,
      -0.014078883454203606,
      0.010051027871668339,
      -0.01862790435552597,
      -0.007396811619400978,
      -0.0026114059146493673,
      0.022588754072785378,
      0.010266938246786594,
      0.010326500050723553,
      0.03475422039628029,
      -0.012887651100754738,
      -0.013073781505227089,
      0.023258822038769722,
      0.0075643290765583515,
      -0.018583232536911964,
      -0.017898274585604668,
      -0.005449890624731779,
      0.004217708948999643,
      -0.0319846048951149,
      0.01240371260792017,
      0.009753219783306122,
      0.0014573989901691675,
      0.012664294801652431,
      -0.014868075959384441,
      -0.001846411032602191,
      -0.028827836737036705,
      0.018315205350518227,
      -0.0012377654202282429,
      0.004809602629393339,
      -0.027979083359241486,
      -0.0046495310962200165,
      -0.023943781852722168,
      -0.0170644111931324,
      0.0022372843232005835,
      0.009857452474534512,
      0.002752864733338356,
      0.011778315529227257,
      -0.011301822029054165,
      0.0017933639464899898,
      -0.010192486457526684,
      -0.0002731459680944681,
      0.004429897293448448,
      0.025745520368218422,
      0.013944869861006737,
      -0.010028691962361336,
      -0.04008498787879944,
      0.0011400470975786448,
      -0.0001582106197020039,
      -0.004738873336464167,
      -0.03219306841492653,
      -0.00810782890766859,
      -0.019506439566612244,
      0.013639616779983044,
      0.0008571292855776846,
      0.026743179187178612,
      0.038059890270233154,
      0.0047314283438026905,
      -0.002101409249007702,
      0.01301421970129013,
      0.028321562334895134,
      -0.00821206159889698,
      -0.04136556386947632,
      0.019431985914707184,
      -0.0074638184159994125,
      0.007735568564385176,
      -0.004656976088881493,
      0.0024736695922911167,
      0.06006791815161705,
      -0.005926383659243584,
      -0.00863643828779459,
      0.007411702070385218,
      0.02488187700510025,
      -0.012031452730298042,
      0.011718753725290298,
      -0.01749623380601406,
      -0.022946123033761978,
      7.637152157258242e-05,
      0.033443864434957504,
      -0.012076123617589474,
      0.0006077149300836027,
      0.021352849900722504,
      0.0034676045179367065,
      0.01585828885436058,
      -0.0037188802380114794,
      -0.03618369996547699,
      0.012686630710959435,
      -0.021025260910391808,
      -0.019506439566612244,
      0.010639199055731297,
      0.00874067097902298,
      0.00540521927177906,
      -0.002298707142472267,
      0.013498158194124699,
      0.027487698942422867,
      -0.010475404560565948,
      0.04178249463438988,
      -0.027636602520942688,
      0.04869164526462555,
      0.008360966108739376,
      0.02089124731719494,
      0.010743431746959686,
      0.0037728578317910433,
      0.019729794934391975,
      0.03797055035829544,
      -0.02936389110982418,
      -0.008100383915007114,
      0.005993390455842018,
      0.00474631879478693,
      -0.010118034668266773,
      0.0032163287978619337,
      -0.015366904437541962,
      -0.002507172990590334,
      -0.024628739804029465,
      0.03475422039628029,
      0.03100183606147766,
      0.004965952131897211,
      -0.030376438051462173,
      0.017287766560912132,
      -0.006019448861479759,
      -0.03937024623155594,
      0.014942527748644352,
      0.031031617894768715,
      -0.017079301178455353,
      -0.0032945035491138697,
      0.022156931459903717,
      -0.016022082418203354,
      0.017526013776659966,
      -0.007601554971188307,
      0.023229042068123817,
      -0.021442191675305367,
      0.007862136699259281,
      -0.009768109768629074,
      0.016126316040754318,
      -0.017823822796344757,
      -0.008517315611243248,
      0.003912455402314663,
      -0.013550274074077606,
      0.04800668731331825,
      0.00671929819509387,
      -0.011651746928691864,
      -0.0014257568400353193,
      -0.02182934246957302,
      -0.008100383915007114,
      -0.0030264761298894882,
      0.04997222125530243,
      -0.013691732659935951,
      0.011473061516880989,
      -0.02267809584736824,
      -0.039072439074516296,
      -0.015217999927699566,
      -0.026192232966423035,
      0.005941274110227823,
      -0.009358623065054417,
      0.0038417261093854904,
      -0.03931068629026413,
      -0.014614938758313656,
      -0.027770616114139557,
      -0.001883637043647468,
      -0.00225775851868093,
      -0.025909315794706345,
      -0.010460513643920422,
      0.02154642529785633,
      0.005937551613897085,
      0.03246109560132027,
      0.013795966282486916,
      -0.03034665808081627,
      0.026906972751021385,
      -0.02894696034491062,
      -0.003942236304283142,
      -0.01621565781533718,
      0.006127404049038887,
      -0.023154590278863907,
      0.01500208955258131,
      0.024688301607966423,
      0.0058370414189994335,
      0.0031902706250548363,
      0.02446494624018669,
      -0.005714195314794779,
      -0.014227787964046001,
      0.000655178097076714,
      0.012180356308817863,
      -0.01655813679099083,
      0.007095281034708023,
      -0.0018547868821769953,
      0.024509616196155548,
      -0.0022763716988265514,
      -0.012589843012392521,
      0.001128879259340465,
      -0.02678784914314747,
      -0.01578383520245552,
      0.00673418864607811,
      0.025283917784690857,
      -0.0020381249487400055,
      -0.004191650543361902,
      -0.001335483742877841,
      0.03752383589744568,
      -0.010132924653589725,
      -0.015039315447211266,
      -0.029170315712690353,
      -0.009902123361825943,
      0.020653000101447105,
      -0.013364143669605255,
      0.007765349466353655,
      0.011428390629589558,
      0.016304999589920044,
      -0.015009534545242786,
      0.05467759072780609,
      -0.01091467123478651,
      -0.00416187010705471,
      0.014875520952045918,
      0.034575533121824265,
      -0.004187928047031164,
      -0.001335483742877841,
      -0.02601354755461216,
      0.00792914442718029,
      0.008487534709274769,
      0.02239517867565155,
      0.02068278193473816,
      -0.012150575406849384,
      0.006417767144739628,
      -0.034367069602012634,
      0.0020734898280352354,
      -0.015262671746313572,
      0.010981678031384945,
      0.013609835878014565,
      0.004634640645235777,
      0.012656849808990955,
      -0.018315205350518227,
      -0.03034665808081627,
      -0.027830177918076515,
      0.02339283563196659,
      0.027904631569981575,
      -0.004485736601054668,
      -0.01983402855694294,
      -0.010758321732282639,
      0.0181216299533844,
      0.030525343492627144,
      0.029185205698013306,
      -0.017957836389541626,
      0.024152247235178947,
      0.008398192003369331,
      0.0014127277536317706,
      0.0022335615940392017,
      0.011473061516880989,
      0.0051111336797475815,
      0.08058690279722214,
      0.026058219373226166,
      0.0016993682365864515,
      -0.014689390547573566,
      -0.03121030144393444,
      -0.033086493611335754,
      0.005204198881983757,
      0.008993808180093765,
      -0.005952442064881325,
      0.012545171193778515,
      -0.007944034412503242,
      0.016394343227148056,
      -0.0022745102178305387,
      0.020504096522927284,
      -0.03582632914185524,
      0.007824910804629326,
      -0.006667181849479675,
      -0.008078048005700111,
      -0.011272041127085686,
      -0.017823822796344757,
      -0.02147197350859642,
      -0.007743014022707939,
      -0.024360712617635727,
      -0.007266520522534847,
      -0.025715740397572517,
      0.011100801639258862,
      0.02695164456963539,
      -0.03100183606147766,
      -0.019431985914707184,
      -0.009812780655920506,
      0.013267355971038342,
      0.006306088995188475,
      0.010408397763967514,
      -0.0017775428714230657,
      -0.027279233559966087,
      0.02836623415350914,
      -0.030108410865068436,
      -0.002669106237590313,
      -0.00792169850319624,
      -0.00026756207807920873,
      0.005442445166409016,
      0.03362254798412323,
      -0.010237157344818115,
      -0.032163288444280624,
      -0.0033038100227713585,
      0.012277144007384777,
      -0.019283082336187363,
      -0.004314496647566557,
      0.005468503572046757,
      -0.02657938376069069,
      0.021233726292848587,
      -0.048810768872499466,
      0.014838295057415962,
      0.0019013193668797612,
      0.005059017334133387,
      0.009016144089400768,
      -0.021412411704659462,
      -0.026534711942076683,
      0.0033950137440115213,
      -0.0019022499909624457,
      -0.018866151571273804,
      0.030019069090485573,
      0.015560479834675789,
      0.0397871769964695,
      0.004619750194251537,
      0.0049510616809129715,
      -0.05500517785549164,
      0.0035476405173540115,
      0.026251794770359993,
      0.02580508217215538,
      -0.031388986855745316,
      0.010773212648928165,
      0.00892680138349533,
      -0.01030416414141655,
      -0.013535384088754654,
      0.0291405338793993,
      -0.002503450494259596,
      0.04014454782009125,
      0.0004927795380353928,
      -0.03171657770872116,
      0.014294794760644436,
      0.005554123315960169,
      0.006186965852975845,
      0.03823857754468918,
      -0.009224609471857548,
      -0.007437760476022959,
      -0.008897020481526852,
      -0.017436672002077103,
      0.004213986452668905,
      -0.00014797346375416964,
      -0.017451561987400055,
      0.022648315876722336,
      -0.011212479323148727,
      0.015441356226801872,
      -0.0038826747331768274,
      -0.015947630628943443,
      -0.012805753387510777,
      0.01116036344319582,
      -0.006280031055212021,
      -0.017034631222486496,
      -0.027681274339556694,
      0.0216804388910532,
      -0.010668979957699776,
      0.011346492916345596,
      -0.00028919969918206334,
      -0.010400951839983463,
      0.009894678369164467,
      -0.0191937405616045,
      -0.002049292903393507,
      -0.012143130414187908,
      -0.0017068133456632495,
      -0.012068678624927998,
      -0.015016979537904263,
      -0.02672828733921051,
      0.010371171869337559,
      -1.2789176253136247e-05,
      -0.00789191760122776,
      0.008070603013038635,
      0.005163250025361776,
      -0.015947630628943443,
      -0.011026349849998951,
      0.033086493611335754,
      0.011621966026723385,
      0.0030153081752359867,
      0.007221849635243416,
      0.009336288087069988,
      0.0028049813117831945,
      0.009984021075069904,
      0.037851426750421524,
      0.00556529127061367,
      0.01282808929681778,
      0.020131835713982582,
      -0.013185459189116955,
      -0.01968512311577797,
      0.02651982195675373,
      -0.03558808192610741,
      0.027189891785383224,
      0.01804717816412449,
      -0.01486063003540039,
      -0.009589425288140774,
      0.0013224546564742923,
      -0.008390747010707855,
      0.0017933639464899898,
      0.016156096011400223,
      0.010259493254125118,
      -0.009976575151085854,
      -0.007839801721274853,
      0.008897020481526852,
      0.009403294883668423,
      0.04273547977209091,
      -0.018613014370203018,
      0.020221179351210594,
      0.01734732836484909,
      -0.0032293580006808043,
      -0.006667181849479675,
      -0.007914253510534763,
      0.015143548138439655,
      -0.01791316457092762,
      -0.0017077440861612558,
      -0.02288656122982502,
      -0.0018957355059683323,
      0.020414752885699272,
      0.009954240173101425,
      -0.021293288096785545,
      0.002540676388889551,
      -0.006146017462015152,
      -0.0166921503841877,
      0.002831039484590292,
      -0.020429644733667374,
      0.0291554257273674,
      0.002047431655228138,
      -0.03782164305448532,
      -0.02004249393939972,
      -0.01261217799037695,
      0.013021664693951607,
      0.005714195314794779,
      0.008725780993700027,
      -0.0012489332584664226,
      0.010572192259132862,
      -0.0209805890917778,
      0.01834498718380928,
      -0.01742178201675415,
      -0.04065082222223282,
      0.01396720577031374,
      0.00017158871924038976,
      0.01518077403306961,
      -0.023139698430895805,
      -0.0077281235717237,
      -0.010542411357164383,
      -0.0043256646022200584,
      0.015694493427872658,
      0.012865315191447735,
      0.008614103309810162,
      -0.008599212393164635,
      0.02601354755461216,
      0.019938260316848755,
      0.005047849379479885,
      -0.017689809203147888,
      0.00012482352030929178,
      0.013624725863337517,
      -0.0038026387337595224,
      0.019163958728313446,
      0.014935082755982876,
      -0.013989541679620743,
      0.022305836901068687,
      -0.022008027881383896,
      0.0001883404329419136,
      0.028053535148501396,
      0.0080035962164402,
      -0.012046342715620995,
      0.0031884093768894672,
      0.014324575662612915,
      0.023303493857383728,
      0.027532370761036873,
      0.010505185462534428,
      0.013520493172109127,
      -0.019223520532250404,
      0.0015002089785411954,
      0.0010730403009802103,
      0.015902958810329437,
      -0.002510895486921072,
      -0.019372424110770226,
      -0.01868746615946293,
      -0.000666811247356236,
      0.00556529127061367,
      -0.027040986344218254,
      -0.03954893350601196,
      -0.007523380219936371,
      0.006868202239274979,
      0.017526013776659966,
      -0.00810782890766859,
      -0.0014453005278483033,
      0.0419611781835556,
      -0.021069932729005814,
      -0.011621966026723385,
      0.017451561987400055,
      0.02288656122982502,
      -0.005520619917660952,
      -0.017674917355179787,
      -0.014949972741305828,
      -0.0033354521729052067,
      -0.016170985996723175,
      -0.004377780947834253,
      0.006953821983188391,
      0.00977555476129055,
      -0.0001670517958700657,
      -0.013185459189116955,
      -0.0077057876624166965,
      -0.0002657007717061788,
      -0.0031437380239367485,
      0.00019427333609201014,
      -0.014108664356172085,
      -0.014294794760644436,
      -0.012597288005053997,
      -0.004764931742101908,
      0.011502842418849468,
      -0.00593382865190506,
      0.013773630373179913,
      0.045237068086862564,
      -0.014689390547573566,
      0.012306924909353256,
      -0.010393506847321987,
      0.0038863972295075655,
      0.03293759003281593,
      0.008249287493526936,
      0.009648986160755157,
      -0.008807677775621414,
      -0.014905301854014397,
      -0.015471137128770351,
      -0.02047431468963623,
      -0.0216804388910532,
      0.02196335606276989,
      -0.03204416483640671,
      -0.007307469379156828,
      0.02367575466632843,
      -0.004917558282613754,
      0.0012880205176770687,
      -0.0037821645382791758,
      0.013885308057069778,
      -0.0043293870985507965,
      0.017392000183463097,
      0.013133342377841473,
      -0.005967332515865564,
      -0.009574534371495247,
      0.008628993295133114,
      0.033175837248563766,
      -0.018613014370203018,
      0.012150575406849384,
      0.007795130368322134,
      -0.013259910978376865,
      -0.00031944585498422384,
      0.0013736403780058026,
      -0.006101346109062433,
      -0.013185459189116955,
      -0.02714521996676922,
      0.014972308650612831,
      0.013371589593589306,
      2.6974328193318797e-06,
      0.007147397380322218,
      -0.022276055067777634,
      -0.003462020540609956,
      0.026638945564627647,
      0.004761208780109882,
      0.022916343063116074,
      -0.018642794340848923,
      0.014741507358849049,
      0.010274384170770645,
      -0.02922987751662731,
      0.00977555476129055,
      -0.005397774279117584,
      0.0023675754200667143,
      0.00444106524810195,
      -0.015798727050423622,
      0.02793441154062748,
      -0.01684105582535267,
      -0.004117198754101992,
      0.0012312509352341294,
      -0.008591767400503159,
      -0.0113688288256526,
      0.006592729594558477,
      -0.003908732905983925,
      -0.010691314935684204,
      -0.039280906319618225,
      0.024256478995084763,
      0.00372446421533823,
      -0.0009394919034093618,
      -0.016394343227148056,
      -0.007944034412503242,
      -0.007501044776290655,
      -0.0044931815937161446,
      0.0034378236159682274,
      -0.010467958636581898,
      -0.03811945393681526,
      0.016111424192786217,
      -0.0005104619194753468,
      0.027174999937415123,
      0.0031046506483107805,
      0.022216493263840675,
      0.005881712306290865,
      0.00022486847592517734,
      -0.023511959239840508,
      0.008308849297463894,
      -0.022588754072785378,
      0.019015055149793625,
      0.01091467123478651,
      0.021978246048092842,
      -0.007877027615904808,
      -0.018806589767336845,
      -0.01343859639018774,
      -0.007676006760448217,
      -0.02936389110982418,
      0.03511159121990204,
      0.0017328716348856688,
      -0.032520659267902374,
      0.01620076783001423,
      0.0007980329683050513,
      0.008413081988692284,
      0.017719589173793793,
      0.005215366370975971,
      0.02218671329319477,
      0.04237810894846916,
      -0.008785342797636986,
      -0.020206287503242493,
      -0.005371715873479843,
      -0.001025577075779438,
      -0.013490712270140648,
      -0.030406219884753227,
      0.0007412632694467902,
      0.00517069548368454,
      0.020236069336533546,
      0.03027220629155636,
      0.010333945043385029,
      0.004560188390314579,
      0.028127986937761307,
      -0.014547931961715221,
      -0.02290145307779312,
      -0.006373095791786909,
      -0.00474631879478693,
      -0.0017654444091022015,
      -0.0110189039260149,
      0.006871924735605717,
      0.01742178201675415,
      -0.00707294512540102,
      -0.007489876821637154,
      -0.027040986344218254,
      -0.04985309764742851,
      -0.013557719066739082,
      0.0216804388910532,
      0.017898274585604668,
      0.006901705637574196,
      0.019848918542265892,
      -0.03475422039628029,
      -0.025179686024785042,
      -0.014972308650612831,
      0.019804246723651886,
      0.00740797957405448,
      -0.021725110709667206,
      -0.01748134195804596,
      -0.017302658408880234,
      -0.02815776690840721,
      -0.019461767747998238,
      0.015262671746313572,
      0.0058184280060231686,
      -0.000781746581196785,
      0.002985527506098151,
      0.008234397508203983,
      -0.006857034284621477,
      -0.021948466077446938,
      -0.0026765514630824327,
      -0.023080136626958847,
      0.004857996478676796,
      -0.0284257959574461,
      -0.018806589767336845,
      -0.005263760220259428,
      0.0083535211160779,
      -0.007203236222267151,
      -0.022663205862045288,
      0.022707877680659294,
      -0.029944617301225662,
      -0.011830431409180164,
      -0.01932775415480137,
      -0.02375020645558834,
      0.02117416448891163,
      -0.009529863484203815,
      0.028842726722359657,
      -0.017019739374518394,
      -0.005628575570881367,
      -0.014533041045069695,
      0.02047431468963623,
      0.0001786849315976724,
      -0.018017398193478584,
      0.011815541423857212,
      0.01091467123478651,
      -1.7202495655510575e-05,
      -0.015545588918030262,
      0.015158439055085182,
      -0.0066001745872199535,
      0.006860756780952215,
      -0.0209805890917778,
      -0.0022447295486927032,
      0.005345657467842102,
      -0.009217164479196072,
      -0.025849753990769386,
      -0.0037486611399799585,
      0.006801195442676544,
      -0.014339465647935867,
      -0.022216493263840675,
      0.014801069162786007,
      -0.0023899110965430737,
      0.00938095897436142,
      0.007534548174589872,
      -0.0028775720857083797,
      -0.013736404478549957,
      -0.003039505099877715,
      -0.002760309958830476,
      0.00469047948718071,
      -0.005807260517030954,
      0.009135267697274685,
      -0.03668997436761856,
      0.0026337415911257267,
      0.0014183116145431995,
      -0.0042661027982831,
      0.00526003772392869,
      -0.014317130669951439,
      -0.0016509743873029947,
      0.01560515072196722,
      0.002996695227921009,
      0.005382883828133345,
      -0.012746191583573818,
      -0.005360547918826342,
      0.0037132962606847286,
      0.00877789780497551,
      -0.001577452989295125,
      0.0030711472500115633,
      -0.004902667831629515,
      -0.009045924991369247,
      -0.0011567987967282534,
      -0.004898945335298777,
      -0.02537326142191887,
      -0.012924876995384693,
      -0.005457335617393255,
      0.0003510879760142416,
      0.006492219399660826,
      -0.010974233038723469,
      -0.009403294883668423,
      0.05735786259174347,
      0.019863808527588844,
      -0.016096534207463264,
      -0.002375020645558834,
      0.018523670732975006,
      -0.011294377036392689,
      -0.0011865796986967325,
      -0.03654107078909874,
      0.0018277979688718915,
      0.00074870849493891,
      -0.0003299156669527292,
      0.010177596472203732,
      -0.0011958861723542213,
      0.0017673056572675705,
      0.010185041464865208,
      -0.016617698594927788,
      -0.0025295086670666933,
      -0.022573864087462425,
      0.027026096358895302,
      0.0013717791298404336,
      -0.02928943932056427,
      0.008271623402833939,
      -0.0054945615120232105,
      0.005743976216763258,
      0.001214499119669199,
      0.01301421970129013,
      0.011309267021715641,
      -0.0008082701242528856,
      0.02281210944056511,
      0.004638363141566515,
      0.0019469212274998426,
      -0.00673418864607811,
      -0.0103116100654006,
      0.01698995940387249,
      0.008978918194770813,
      0.018181191757321358,
      0.018374767154455185,
      0.004065082408487797,
      0.01932775415480137,
      0.011614521034061909,
      0.001999037805944681,
      -0.007474986370652914,
      0.0010758321732282639,
      0.011123137548565865,
      -0.019208630546927452,
      -0.0002463897690176964,
      -0.0145777128636837,
      0.007914253510534763,
      -0.005602517165243626,
      -0.014227787964046001,
      -0.0063805412501096725,
      -0.008599212393164635,
      -0.005371715873479843,
      0.020131835713982582,
      -0.009723438881337643,
      0.007504767272621393,
      0.007936589419841766,
      -0.032163288444280624,
      0.006570394150912762,
      -0.00370398978702724,
      0.010214822366833687,
      0.012202692218124866,
      -0.03278868645429611,
      0.013706623576581478,
      -0.025790192186832428,
      -0.008681110106408596,
      -0.017228206619620323,
      0.020876357331871986,
      -0.012597288005053997,
      0.01258239708840847,
      0.011487952433526516,
      0.008435417897999287,
      0.0017849880969151855,
      0.00417676055803895,
      -0.0032535549253225327,
      -0.007973815314471722,
      0.0003631864383351058,
      0.002174000022932887,
      -0.007147397380322218,
      -0.0059785000048577785,
      0.0009567089146003127,
      0.01996804215013981,
      0.024345822632312775,
      0.0010348835494369268,
      -0.035439178347587585,
      -0.014480925165116787,
      0.00226520374417305,
      0.023988451808691025,
      0.03335452079772949,
      -0.007229294627904892,
      0.011071020737290382,
      -0.002263342496007681,
      0.011100801639258862,
      -0.008785342797636986,
      0.008919356390833855,
      0.004656976088881493,
      0.010319055058062077,
      0.009574534371495247,
      0.0077057876624166965,
      -0.004076249897480011,
      0.020176507532596588,
      0.003575559938326478,
      -0.00225775851868093,
      -0.0016854084096848965,
      0.009440520778298378,
      -0.012701520696282387,
      0.02239517867565155,
      -0.016736822202801704,
      0.007229294627904892,
      -0.014116110280156136,
      -0.009984021075069904,
      0.0050329589284956455,
      0.03070402704179287,
      0.007582942023873329,
      0.018315205350518227,
      0.013676842674612999,
      -0.024360712617635727,
      -0.0227376576513052,
      -0.019938260316848755,
      -0.017868492752313614,
      -0.003942236304283142,
      -0.014793623238801956,
      -0.017377110198140144,
      0.020161617547273636,
      -0.0006677418714389205,
      0.0025965154636651278,
      0.00698360288515687,
      0.0026784127112478018,
      -0.004243767354637384,
      0.009127821773290634,
      -0.001583036850206554,
      -0.002708193613216281,
      -0.0030078631825745106,
      0.003737493185326457,
      0.006313534453511238,
      -0.007810020819306374,
      -0.0015755916247144341,
      -0.0018045316683128476,
      0.0011335326125845313,
      0.00343968509696424,
      -0.013818301260471344,
      -0.012277144007384777,
      0.0008859794470481575,
      -0.022410068660974503,
      0.027770616114139557,
      -0.01076576765626669,
      -0.006015726365149021,
      0.0033149777445942163,
      0.017228206619620323,
      -0.003043227829039097,
      0.014644719660282135,
      -0.009559644386172295,
      -0.020280739292502403,
      0.021650657057762146,
      0.010557301342487335,
      0.009500082582235336,
      0.0013755017425864935,
      0.014004431664943695,
      0.00977555476129055,
      -0.0073000239208340645,
      -0.021129492670297623,
      0.0028198715299367905,
      -0.021293288096785545,
      -0.035439178347587585,
      -0.01158474013209343,
      0.0177642609924078,
      0.010400951839983463,
      0.007367031183093786,
      0.0020437089260667562,
      0.0038044999819248915,
      -0.014272458851337433,
      -0.005304709076881409,
      -0.010698760859668255,
      -0.019372424110770226,
      0.016096534207463264,
      0.021844232454895973,
      0.005215366370975971,
      0.018166301771998405,
      -0.011085910722613335,
      0.014324575662612915,
      -0.013393924571573734,
      0.013148233294487,
      0.007631335873156786,
      -0.01229947991669178,
      0.01553069893270731,
      0.017109083011746407,
      -0.006592729594558477,
      0.005721640307456255,
      0.0154562471434474,
      -0.005461058113723993,
      -0.018166301771998405,
      0.009812780655920506,
      0.010557301342487335,
      -0.027323905378580093,
      0.005122301634401083,
      -0.025566836819052696,
      -0.0004725378821603954,
      0.007869582623243332,
      0.012887651100754738,
      -0.005870544817298651,
      -0.010185041464865208,
      -0.027770616114139557,
      0.0033484811428934336,
      0.009946794249117374,
      0.0076462263241410255,
      -0.008256733417510986,
      0.0024029400665313005,
      9.556619625072926e-05,
      0.02445005439221859,
      0.009194828569889069,
      -0.039429809898138046,
      0.019029945135116577,
      0.0004913835437037051,
      0.008710891008377075,
      -0.011994225904345512,
      0.02934900112450123,
      0.004656976088881493,
      -0.003488078946247697,
      0.015061651356518269,
      0.004113476257771254,
      -0.015091431327164173,
      -0.002170277526602149,
      0.021099712699651718,
      0.00230056862346828,
      0.01870235614478588,
      0.007884472608566284,
      0.01733243837952614,
      -0.008480088785290718,
      0.010408397763967514,
      0.00945541076362133,
      0.025760412216186523,
      -0.004191650543361902,
      0.0040315790101885796,
      -0.012627068907022476,
      0.02309502847492695,
      -0.00024615711299702525,
      0.003657457185909152,
      0.0018585094949230552,
      -0.0063544828444719315,
      0.016975069418549538,
      -0.005464781075716019,
      0.0022335615940392017,
      -0.04890010878443718,
      -0.0038826747331768274,
      -0.012336705811321735,
      0.01649857498705387,
      -0.0021516643464565277,
      0.014614938758313656,
      0.020846575498580933,
      -3.2543692213948816e-05,
      0.008070603013038635,
      0.008889575488865376,
      -0.009008699096739292,
      0.004898945335298777,
      -0.003778441809117794,
      -0.0047909896820783615,
      0.022782329469919205,
      -0.01215802039951086,
      -0.0003804034786298871,
      0.00442617479711771,
      -0.0034341011196374893,
      -0.002242868300527334,
      -0.01478617824614048,
      -0.00639915419742465,
      0.006347037851810455,
      0.010512630455195904,
      -0.014830849133431911,
      0.005546678323298693,
      0.00385661656036973,
      0.00917249359190464,
      0.007437760476022959,
      0.0038454486057162285,
      -0.016245437785983086,
      -0.006946376990526915,
      0.0010023107752203941,
      0.009678767062723637,
      0.004340555053204298,
      0.013408815488219261,
      -0.00927672628313303,
      0.020846575498580933,
      -0.012664294801652431,
      0.018300315365195274,
      -0.00185199489351362,
      -0.018717246130108833,
      0.006213024258613586,
      -0.012411157600581646,
      -0.008040822111070156,
      0.02409268543124199,
      0.005066462326794863,
      -0.00789191760122776,
      -0.03389057517051697,
      -0.0070022158324718475,
      0.01200911682099104,
      -0.0053568254224956036,
      -0.0019618116784840822,
      -0.01507654134184122,
      0.0006709991721436381,
      0.01983402855694294,
      0.009254390373826027,
      -0.00451551703736186,
      -0.027115438133478165,
      -0.0016137482598423958,
      0.017377110198140144,
      -0.012962102890014648,
      -0.001762652420438826,
      0.0025202021934092045,
      0.00012342755508143455,
      0.020742343738675117,
      -0.002380604390054941,
      0.010795548558235168,
      -0.005014345981180668,
      0.008517315611243248,
      0.0031846866477280855,
      0.00501062348484993,
      -0.00924694538116455,
      0.0038789522368460894,
      -0.015679603442549706,
      -0.01740689016878605,
      -0.0015095154521986842,
      -0.005807260517030954,
      0.0025146182160824537,
      0.0022503132931888103,
      -0.011785760521888733,
      -0.007471263874322176,
      0.022216493263840675,
      -0.0064363800920546055,
      0.006428935099393129,
      -0.007311191875487566,
      0.00536427041515708,
      0.006175797898322344,
      0.014443699270486832,
      0.0044671231880784035,
      -0.01698995940387249,
      0.014205452054738998,
      0.004042746499180794,
      0.007839801721274853,
      -0.007419147528707981,
      0.0083535211160779,
      0.007028274238109589,
      0.005665801465511322,
      0.013959760777652264,
      -0.014637274667620659,
      0.0009892816888168454,
      0.0046495310962200165,
      -0.03171657770872116,
      0.012165466323494911,
      -0.02465852163732052,
      -0.003648150712251663,
      0.0012852286454290152,
      0.01989358849823475,
      -0.00038342809421010315,
      -0.022216493263840675,
      0.014503260143101215,
      -0.007914253510534763,
      0.01627521961927414,
      -0.0049547841772437096,
      0.025998657569289207,
      0.003577421186491847,
      0.004925003740936518,
      0.0009250668226741254,
      0.02934900112450123,
      -0.0266538355499506,
      -0.02154642529785633,
      0.01634967140853405,
      0.008383301086723804,
      0.0003478307044133544,
      0.012120794504880905,
      -0.006897983141243458,
      -0.010877445340156555,
      0.013498158194124699,
      -0.010393506847321987,
      0.012671739794313908,
      -0.004828216042369604,
      -0.024509616196155548,
      -0.009053369984030724,
      0.01785360276699066,
      0.007005938328802586,
      -0.006332147400826216,
      -0.016587918624281883,
      0.0010367449140176177,
      0.02032541111111641,
      0.006994770839810371,
      -0.005721640307456255,
      -0.015366904437541962,
      0.0019134178292006254,
      -0.013066335581243038,
      0.002134912647306919,
      -0.004333109594881535,
      0.0017784734955057502,
      -0.00831629429012537,
      0.00639915419742465,
      0.02290145307779312,
      -0.013527938164770603,
      -0.011674082837998867,
      -0.014942527748644352,
      0.006562948692589998,
      0.00042274806764908135,
      0.01996804215013981,
      0.006034339312463999,
      -0.000861782522406429,
      -0.006801195442676544,
      0.02309502847492695,
      0.008450308814644814,
      0.0009050578228197992,
      0.006953821983188391,
      -0.008733225986361504,
      0.0011670360108837485,
      0.023705534636974335,
      -0.000471839914098382,
      -0.003398736473172903,
      0.001491833128966391,
      0.0024476114194840193,
      0.020846575498580933,
      -0.010683869943022728,
      0.0104902945458889,
      0.00035527590080164373,
      0.019804246723651886,
      -0.00311954109929502,
      0.02452450804412365,
      -0.015679603442549706,
      0.008011041209101677,
      0.0017496233340352774,
      -0.012887651100754738,
      -0.0033112552482634783,
      0.018657686188817024,
      -0.00845775380730629,
      0.018866151571273804,
      -0.003657457185909152,
      -0.0007394019630737603,
      0.008949137292802334,
      0.0035401952918618917,
      0.007765349466353655,
      -0.004906390327960253,
      -0.008398192003369331,
      -0.001705882721580565,
      0.00386406178586185,
      0.0026895804330706596,
      0.019253302365541458,
      -0.010870000347495079,
      -0.0029799435287714005,
      -0.0024345822166651487,
      -0.033592768013477325,
      -0.0007863998180255294,
      -0.018642794340848923,
      -0.025492383167147636,
      -0.003210744820535183,
      -0.00832374021410942,
      -0.019223520532250404,
      0.00016204956045839936,
      -0.008569431491196156,
      -0.0023638526909053326,
      -0.0003129313117824495,
      0.0011847183341160417,
      -0.03296737000346184,
      -0.0019134178292006254,
      0.015292452648282051,
      -0.027026096358895302,
      0.00385661656036973,
      0.0017179811839014292,
      0.008420527912676334,
      -0.010438178665935993,
      0.0083535211160779,
      -0.0113688288256526,
      0.0018371044425293803,
      -0.0008631785167381167,
      -0.005092520732432604,
      0.002220532624050975,
      0.013155678287148476,
      0.008673664182424545,
      0.03153789043426514,
      -0.01081043854355812,
      0.002428998239338398,
      0.014555376954376698,
      0.0011595907853916287,
      0.02963191829621792,
      0.013393924571573734,
      -0.00499573303386569,
      0.018598124384880066,
      0.0025257859379053116,
      0.008465198799967766,
      -0.012225027196109295,
      0.012500500306487083,
      -0.01186765730381012,
      0.009090595878660679,
      -0.02765149436891079,
      -0.0038119452074170113,
      -0.021695328876376152,
      -0.004861719440668821,
      0.019536219537258148,
      0.005621130112558603,
      0.010922116227447987,
      0.005289818625897169,
      0.010572192259132862,
      -0.0015299897640943527,
      0.017109083011746407,
      -0.00011778547923313454,
      0.0004164661804679781,
      -0.024628739804029465,
      0.004478291142731905,
      0.008673664182424545,
      -0.004694201983511448,
      2.7890439014299773e-05,
      0.016334781423211098,
      0.02026584930717945,
      0.004768654238432646,
      -0.005185585934668779,
      0.01481595914810896,
      0.0031120958738029003,
      0.0076201679185032845,
      0.01599230244755745,
      -0.0020772123243659735,
      -0.005073907785117626,
      -0.01664748042821884,
      -0.010862555354833603,
      -0.0011996087851002812,
      0.011629411019384861,
      0.004764931742101908,
      0.021069932729005814,
      0.011071020737290382,
      0.005598794668912888,
      0.0019152791937813163,
      -0.0181216299533844,
      -0.009098040871322155,
      -0.016081644222140312,
      0.00485055148601532,
      0.011651746928691864,
      0.01840454898774624,
      0.007988705299794674,
      0.019923370331525803,
      0.005349380429834127,
      0.007370753679424524,
      -0.02162087708711624,
      0.020370082929730415,
      -0.02005738392472267,
      -0.011190144345164299,
      -0.015240335837006569,
      -0.002749142237007618,
      0.005375438369810581,
      0.006778859533369541,
      -0.027383465319871902,
      -0.019446877762675285,
      0.003942236304283142,
      -0.001251725247129798,
      0.012463274411857128,
      0.0002089310873998329,
      -0.007556883618235588,
      -0.011406054720282555,
      0.011592185124754906,
      -0.0008431695168837905,
      -0.005300986580550671,
      0.01428734976798296,
      0.00895658228546381,
      0.003447130089625716,
      -0.0021963356994092464,
      -0.019848918542265892,
      -0.02083168551325798,
      0.03192504122853279,
      0.01104868482798338,
      -0.0053531029261648655,
      0.019283082336187363,
      0.020563658326864243,
      -0.00988723337650299,
      0.0012014700332656503,
      0.012872760184109211,
      0.001173550495877862,
      -0.00698360288515687,
      0.02117416448891163,
      -0.001645390409976244,
      -0.027919521555304527,
      -0.007166010327637196,
      0.002375020645558834,
      0.002754725981503725,
      -0.0077281235717237,
      0.013379034586250782,
      -0.010929562151432037,
      0.004962229635566473,
      0.0009106416837312281,
      0.00755316112190485,
      0.006157184951007366,
      0.028202438727021217,
      -0.01041584275662899,
      4.62998723378405e-05,
      -0.017972726374864578,
      -0.014346911571919918,
      0.010118034668266773,
      0.018568342551589012,
      0.007668561767786741,
      -0.017153752967715263,
      0.015173329040408134,
      0.0005272136186249554,
      0.017823822796344757,
      -0.004124643746763468,
      -0.015352013520896435,
      0.0009957962902262807,
      -0.0003115353174507618,
      -0.012098459526896477,
      0.012031452730298042,
      0.008986363187432289,
      -0.020087163895368576,
      -0.011822986416518688,
      -0.009403294883668423,
      0.009045924991369247,
      0.04806624725461006,
      0.01407143846154213,
      0.01094445213675499,
      0.012448383495211601,
      -0.001686339033767581,
      0.006302366498857737,
      -0.0029278271831572056,
      0.0037896097637712955,
      -0.022931233048439026,
      0.017019739374518394,
      0.03868528828024864,
      0.000916225602850318,
      -0.005140914581716061,
      -0.007575496565550566,
      -0.003994352649897337,
      0.00917249359190464,
      0.002914797980338335,
      -0.016022082418203354,
      -0.007493599317967892,
      0.0017831267323344946,
      0.029825493693351746,
      0.002713777357712388,
      0.016751712188124657,
      0.01165919192135334,
      -0.006283753551542759,
      -0.007113893982023001,
      0.020846575498580933,
      0.019744684919714928,
      0.011748534627258778,
      0.009194828569889069,
      -0.002347100991755724,
      -0.010817883536219597,
      -0.015754055231809616,
      0.0010460513876751065,
      0.006443825550377369,
      -0.021382629871368408,
      0.02651982195675373,
      0.01186765730381012,
      0.003625815035775304,
      -0.022008027881383896,
      -0.008018486201763153,
      -0.004083695355802774,
      -0.008919356390833855,
      0.023586411029100418,
      0.0015858288388699293,
      0.0184938907623291,
      0.013423705473542213,
      -0.026817630976438522,
      -0.016677260398864746,
      0.016379453241825104,
      -0.0059189386665821075,
      -0.0013057029573246837,
      -0.01293232198804617,
      0.034009698778390884,
      0.0151063222438097,
      0.005628575570881367,
      -0.005446168128401041,
      -0.03064446710050106,
      -0.018583232536911964,
      -0.005021790973842144,
      -0.009038479998707771,
      -0.01019993145018816,
      -0.015813617035746574,
      -0.020176507532596588,
      0.005036681424826384,
      0.01081043854355812,
      0.009418184868991375,
      0.007467541377991438,
      0.01663258858025074,
      0.0009995189029723406,
      0.0031046506483107805,
      -0.0037170189898461103,
      0.005367993377149105,
      0.008800232782959938,
      0.021010370925068855,
      0.025283917784690857,
      0.01825564354658127,
      0.007884472608566284,
      0.01009569875895977,
      0.01570938341319561,
      0.008249287493526936,
      0.0054126642644405365,
      -2.6538086785876658e-06,
      0.00582959596067667,
      0.015664713457226753,
      -0.009120376780629158,
      -0.003447130089625716,
      -0.013669397681951523,
      -0.014421363361179829,
      -0.0050552948378026485,
      -0.003905010409653187,
      -0.019670233130455017,
      -0.008383301086723804,
      0.004206540994346142,
      0.017645137384533882,
      -0.018374767154455185,
      -0.004295883700251579,
      -0.005662078969180584,
      0.004213986452668905,
      -0.010937007144093513,
      0.006347037851810455,
      -0.011614521034061909,
      0.0003850567154586315,
      -0.023005684837698936,
      -0.003166073700413108,
      0.013408815488219261,
      0.009284171275794506,
      0.0038826747331768274,
      0.009418184868991375,
      -0.025998657569289207,
      0.0010013801511377096,
      0.011115691624581814,
      -0.013818301260471344,
      -0.017928054556250572,
      -0.015366904437541962,
      -0.006950099486857653,
      0.004764931742101908,
      0.001314078806899488,
      0.0025723185390233994,
      0.01757068559527397,
      -0.007616445422172546,
      -0.01621565781533718,
      -0.020161617547273636,
      -0.008271623402833939,
      -0.01116036344319582,
      0.005416387226432562,
      -0.018151411786675453,
      -0.004433619789779186,
      -0.012306924909353256,
      -0.0007710441132076085,
      -0.0020716283470392227,
      -0.01584339700639248,
      0.004240044392645359,
      -0.012120794504880905,
      -0.003569976193830371,
      0.01678149402141571,
      -0.002136773895472288,
      -0.019446877762675285,
      0.009693657979369164,
      -0.0036500119604170322,
      -0.015240335837006569,
      0.0035141371190547943,
      -0.008115273900330067,
      -0.009894678369164467,
      0.022856781259179115,
      -0.00842797290533781,
      0.0013233852805569768,
      0.008256733417510986,
      -0.014019322581589222,
      -0.02778550796210766,
      0.005881712306290865,
      0.011324157938361168,
      -0.00834607519209385,
      -0.004158147145062685,
      -0.005338212475180626,
      -0.009045924991369247,
      0.014451144263148308,
      0.004753763787448406,
      0.013743849471211433,
      0.03520093113183975,
      -0.01428734976798296,
      -0.004068804904818535,
      -0.04377780854701996,
      0.00598966795951128,
      0.02552216500043869,
      -0.02211226150393486,
      0.017228206619620323,
      -0.00037016632268205285,
      0.009976575151085854,
      0.02217182144522667,
      0.008889575488865376,
      -0.006763969082385302,
      -0.030048849061131477,
      -0.021635767072439194,
      -0.004079972859472036,
      0.016528356820344925,
      -0.0045676338486373425,
      -0.00032921769889071584,
      -0.0040315790101885796,
      0.018285425379872322,
      0.010579637251794338,
      0.002784506883472204,
      -0.005233979318290949,
      -0.002916659228503704,
      0.015083986334502697,
      0.009403294883668423,
      -0.013393924571573734,
      0.006860756780952215,
      -0.01489785686135292,
      0.0065741166472435,
      0.005394051317125559,
      -0.01833009533584118,
      0.006097623612731695,
      0.0034713270142674446,
      0.006075287703424692,
      -0.011093356646597385,
      0.011190144345164299,
      0.004478291142731905,
      -0.001725426409393549,
      -0.007601554971188307,
      0.0005155804683454335,
      -0.010788102634251118,
      0.019595781341195107,
      0.0156349316239357,
      -0.00572536326944828,
      -0.012172911316156387,
      -0.016811273992061615,
      0.004843106027692556,
      -0.02403312362730503,
      0.016513466835021973,
      0.021501753479242325,
      0.0036760703660547733,
      0.03237175568938255,
      -0.016260329633951187,
      -0.02282700128853321,
      0.015352013520896435,
      0.017645137384533882,
      -0.012761082500219345,
      -0.007862136699259281,
      -0.011309267021715641,
      0.02367575466632843,
      -0.0010851387633010745,
      -0.013565164990723133,
      -0.001924585667438805,
      -0.009753219783306122,
      -0.008807677775621414,
      0.01870235614478588,
      -0.023854438215494156,
      -0.021695328876376152,
      -0.0035495017655193806,
      -0.020578548312187195,
      0.02032541111111641,
      -0.023139698430895805,
      0.00999146606773138,
      0.018851259723305702,
      -0.006440103054046631,
      0.01998293213546276,
      -0.0017151891952380538,
      0.008874685503542423,
      -0.0031828253995627165,
      0.007787684909999371,
      0.015232890844345093,
      0.011487952433526516,
      -0.011897438205778599,
      0.001762652420438826,
      0.009656432084739208,
      -0.004154424648731947,
      0.0015104460762813687,
      0.01393742486834526,
      0.0160071924328804,
      0.008696000091731548,
      -0.0045490204356610775,
      0.012887651100754738,
      -9.475187107454985e-05,
      -0.014346911571919918,
      -0.00010452370770508423,
      0.008673664182424545,
      -0.02039986290037632,
      -0.014748952351510525,
      -0.007173455785959959,
      -0.025462603196501732,
      -0.00356439221650362,
      0.00991701427847147,
      -0.015411575324833393,
      -0.03141876682639122,
      -0.014086329378187656,
      -0.010527520440518856,
      -0.005003178026527166,
      -0.026341136544942856,
      0.010482849553227425,
      -0.01676660217344761,
      0.020921027287840843,
      -0.015739165246486664,
      -0.00037481955951079726,
      0.00714367488399148,
      0.021099712699651718,
      0.006991047877818346,
      -0.017674917355179787,
      0.004772376734763384,
      0.0022856781724840403,
      0.010616863146424294,
      0.0007882611243985593,
      0.030882712453603745,
      -0.012217582203447819,
      -0.001380154979415238,
      -0.028485355898737907,
      0.010214822366833687,
      -0.00271005486138165,
      0.027681274339556694,
      0.0001871771237347275,
      0.00831629429012537,
      0.011793205514550209,
      -0.01414589025080204,
      0.002795674605295062,
      -0.0006840282585471869,
      0.008368411101400852,
      0.006991047877818346,
      -0.0108402194455266,
      0.007743014022707939,
      0.007061777636408806,
      -0.0036760703660547733,
      0.011621966026723385,
      -0.0005998043925501406,
      -0.003205161076039076,
      0.011004013940691948,
      -0.01446603424847126,
      0.007735568564385176,
      0.035856109112501144,
      0.014853185042738914,
      0.005952442064881325,
      0.012783418409526348,
      0.019446877762675285,
      -0.01354282908141613,
      -0.001932030892930925,
      -0.004213986452668905,
      -0.006685794796794653,
      0.004444787744432688,
      0.03121030144393444,
      -0.02998928911983967,
      0.04493926092982292,
      -0.01229947991669178,
      0.007206959184259176,
      -0.0020753510762006044,
      -0.008681110106408596,
      0.012545171193778515,
      0.008807677775621414,
      -0.0016491130227223039,
      -0.0019190016901120543,
      -0.0054312776774168015,
      -0.005505729466676712,
      0.0031772414222359657,
      0.0067006852477788925,
      -0.004701647441834211,
      0.00385661656036973,
      0.020102055743336678,
      0.006864479742944241,
      -0.018240753561258316,
      -0.02680274099111557,
      -0.005286096129566431,
      -0.008256733417510986,
      -0.0002682600752450526,
      -0.029840383678674698,
      0.01634967140853405,
      -0.002598376711830497,
      -0.015977410599589348,
      0.01375129446387291,
      0.009730883873999119,
      0.004969674628227949,
      -0.0031437380239367485,
      0.0010525659890845418,
      -0.01375874038785696,
      0.007951479405164719,
      0.002751003485172987,
      0.018151411786675453,
      0.012708965688943863,
      -0.0006146947853267193,
      0.013401370495557785,
      -0.0020362637005746365,
      -0.005792370066046715,
      -0.007906808517873287,
      -0.03027220629155636,
      -0.015337123535573483,
      0.005360547918826342,
      0.004474568646401167,
      0.0003897099813912064,
      -0.02879805490374565,
      0.01404165755957365,
      -0.0021907517220824957,
      -0.0006500594899989665,
      0.01186765730381012,
      0.010750876739621162,
      0.008234397508203983,
      -0.019595781341195107,
      -0.0170644111931324,
      -0.00906826090067625,
      -0.00650338688865304,
      -0.013096116483211517,
      -0.007832356728613377,
      -0.006830976344645023,
      -0.011190144345164299,
      0.025507275015115738,
      -0.008859794586896896,
      0.019521329551935196,
      0.016826163977384567,
      0.0051930309273302555,
      -0.00037621555384248495,
      -0.0023675754200667143,
      0.022231383249163628,
      0.004805880133062601,
      0.004083695355802774,
      -0.014488370157778263,
      0.006830976344645023,
      0.0277259461581707,
      0.00047277056728489697,
      0.03085293248295784,
      0.023794876411557198,
      0.0127983083948493,
      0.01375129446387291,
      -0.002222393872216344,
      0.011279486119747162,
      0.00012842979049310088,
      0.021442191675305367,
      -0.0008217645809054375,
      0.01898527517914772,
      0.014994644559919834,
      0.012232473120093346,
      0.014131000265479088,
      0.031329426914453506,
      -0.003653734689578414,
      -0.014674500562250614,
      -0.011793205514550209,
      -0.0033950137440115213,
      -0.006350760348141193,
      0.014004431664943695,
      0.006816085893660784,
      0.02354174107313156,
      0.03463509678840637,
      -0.0011791344732046127,
      0.032163288444280624,
      0.029244767501950264,
      -0.01158474013209343,
      -0.0017300796462222934,
      0.029736151918768883,
      0.035379618406295776,
      -0.00780257536098361,
      0.0018864289158955216,
      -0.007285133469849825,
      0.007039441727101803,
      0.0047909896820783615,
      -0.018791699782013893,
      0.0019152791937813163,
      -0.006938931532204151,
      -0.005948719102889299,
      -0.003815667936578393,
      -0.013498158194124699,
      0.001967395655810833,
      -0.0028682653792202473,
      0.022127151489257812,
      -0.012135685421526432,
      0.0003780768602155149,
      0.028738493099808693,
      -0.010356280952692032,
      0.00017973191279452294,
      0.009827671572566032,
      0.011793205514550209,
      -0.01091467123478651,
      0.02339283563196659,
      0.009730883873999119,
      -0.008524760603904724,
      -0.010043581947684288,
      0.0037635513581335545,
      -0.002339655766263604,
      0.004508072044700384,
      -0.0002684927312657237,
      -0.003169796196743846,
      0.0030320598743855953,
      -0.002019512001425028,
      -0.009820226579904556,
      -0.026058219373226166,
      -0.004623472690582275,
      0.01841943897306919,
      -0.0018724692054092884,
      0.006674626842141151,
      -0.0011447003344073892,
      -0.017868492752313614,
      -0.0003776115190703422,
      -0.0031772414222359657,
      -0.019595781341195107,
      -0.01698995940387249,
      -0.008859794586896896,
      0.02459895983338356,
      -0.001784057356417179,
      0.0033522038720548153,
      0.016543246805667877,
      -0.00028105650562793016,
      0.005341934971511364,
      0.005126024130731821,
      -0.007333527319133282,
      0.0019915925804525614,
      -0.0398169606924057,
      0.012664294801652431,
      -0.012790863402187824,
      0.01364706177264452,
      0.0038417261093854904,
      0.007884472608566284,
      -0.0037188802380114794,
      0.0085322055965662,
      -0.0013987680431455374,
      -9.027311898535118e-05,
      0.0008240911993198097,
      3.573553385649575e-06,
      0.0266687273979187,
      0.0023117363452911377,
      -0.01063175406306982,
      -0.015947630628943443,
      0.016319891437888145,
      0.013624725863337517,
      0.0206083282828331,
      -0.011636856012046337,
      0.019565999507904053,
      0.006101346109062433,
      -0.013624725863337517,
      -0.0021144384518265724,
      0.02488187700510025,
      -0.009760664775967598,
      0.02373531460762024,
      0.005483394023030996,
      -0.01642412319779396,
      0.007608999963849783,
      -0.020161617547273636,
      0.006737911142408848,
      0.008889575488865376,
      -0.0009548476082272828,
      0.01761535555124283,
      -0.014354356564581394,
      0.0006956614088267088,
      0.010386061854660511,
      -0.006443825550377369,
      -0.0021479418501257896,
      0.012671739794313908,
      0.021769780665636063,
      -0.014719171449542046,
      0.008167390711605549,
      -0.0017970865592360497,
      -0.004764931742101908,
      0.013259910978376865,
      0.00970110297203064,
      0.024360712617635727,
      0.011815541423857212,
      -0.00948519166558981,
      -0.0002598841965664178,
      -0.00977555476129055,
      -0.002924104453995824,
      2.3673426767345518e-05,
      0.014585157856345177,
      0.0042474898509681225,
      0.009157602675259113,
      -0.006548058241605759,
      0.00033549958607181907,
      0.0021256061736494303,
      0.0044075618498027325,
      0.0026504932902753353,
      0.00771323312073946,
      0.0037579676136374474,
      0.003562530968338251,
      0.01940220594406128,
      0.003281474346294999,
      -0.007683452218770981,
      0.000235919957049191,
      0.0038789522368460894,
      0.041901618242263794,
      -0.023794876411557198,
      -0.007795130368322134,
      -0.0008766729733906686,
      -0.020667890086770058,
      0.019580891355872154,
      -0.012880206108093262,
      0.0036704863887280226,
      0.003986907657235861,
      -0.020950809121131897,
      -0.018568342551589012,
      -0.006391709204763174,
      0.004809602629393339,
      -0.0030637020245194435,
      0.003931068349629641,
      -0.01870235614478588,
      0.02153153531253338,
      -0.025343479588627815,
      -0.010721095837652683,
      0.007735568564385176,
      0.000383195438189432,
      0.015947630628943443,
      0.014585157856345177,
      0.00045904345461167395,
      -0.0015244059031829238,
      0.006335869897156954,
      0.014265013858675957,
      -0.012530281208455563,
      -0.018642794340848923,
      -0.01364706177264452,
      -0.021129492670297623,
      -0.00039645720971748233,
      0.020563658326864243,
      -0.008301404304802418,
      -0.0025965154636651278,
      0.004418729338794947,
      0.018374767154455185,
      0.01841943897306919,
      -0.010386061854660511,
      -0.0013029109686613083,
      -0.01044562365859747,
      0.003125125076621771,
      0.009693657979369164,
      -0.00949263758957386,
      0.020876357331871986,
      0.013401370495557785,
      0.0031884093768894672,
      -0.0023638526909053326,
      -0.007370753679424524,
      0.00024220184423029423,
      0.025120124220848083,
      0.01712397299706936,
      -0.018895931541919708,
      0.022692985832691193,
      0.0024531951639801264,
      0.00967132207006216,
      -0.015828507021069527,
      0.02573063038289547,
      -0.008271623402833939,
      -0.0154562471434474,
      0.004984565079212189,
      -0.007571774069219828,
      -0.006097623612731695,
      0.014421363361179829,
      -0.014488370157778263,
      0.016617698594927788,
      -0.02616245299577713,
      -0.011123137548565865,
      -0.0019878698512911797,
      -0.002012066775932908,
      0.024539398029446602,
      -0.013133342377841473,
      0.000697988027241081,
      -0.007690897211432457,
      -0.008725780993700027,
      -0.0006938001024536788,
      0.008465198799967766,
      0.013624725863337517,
      -0.023139698430895805,
      -0.025254137814044952,
      0.010832774452865124,
      -0.0034750497434288263,
      -0.0066820718348026276,
      0.007854691706597805,
      0.010475404560565948,
      0.012805753387510777,
      -0.021710218861699104,
      6.846099131507799e-05,
      -0.0074638184159994125,
      0.014190562069416046,
      -0.01655813679099083,
      0.022052699699997902,
      -0.011219925247132778,
      0.008383301086723804,
      -0.002914797980338335,
      -0.008964027278125286,
      -0.010467958636581898,
      -0.010438178665935993,
      0.001290812506340444,
      0.00198042462579906,
      -0.0008729503606446087,
      -0.006473606452345848,
      0.0005774687742814422,
      0.011376273818314075,
      0.009715992957353592,
      -0.00386406178586185,
      0.024152247235178947,
      0.019431985914707184,
      0.01081043854355812,
      -0.012061232700943947,
      0.003968294709920883,
      0.010103143751621246,
      -0.003931068349629641,
      0.00417676055803895,
      0.005542955361306667,
      0.007035719230771065,
      -0.027249451726675034,
      0.016364561393857002,
      0.0035011079162359238,
      -0.0004802157636731863,
      0.01446603424847126,
      0.004805880133062601,
      -0.00416187010705471,
      0.010899781249463558,
      -0.013513048179447651,
      -0.023779986426234245,
      0.04079972580075264,
      0.013974650762975216,
      -0.01414589025080204,
      -0.009969130158424377,
      0.010974233038723469,
      -0.0003827300970442593,
      -0.02985527366399765,
      0.028053535148501396,
      0.04863208159804344,
      0.011785760521888733,
      0.014748952351510525,
      0.0007403326453641057,
      -0.015150993131101131,
      -0.015902958810329437,
      0.006183243356645107,
      0.004173037596046925,
      0.0016267774626612663,
      0.02395867183804512,
      -0.00410603079944849,
      0.021352849900722504,
      -0.019744684919714928,
      -0.01155495923012495,
      -0.003663041163235903,
      0.00019857758888974786,
      -0.009045924991369247,
      -0.004779822193086147,
      0.009023589082062244,
      -0.0004871956480201334,
      -0.004303328692913055,
      -0.004563910886645317,
      -0.029617028310894966,
      -0.019357534125447273,
      0.0017486927099525928,
      -0.01200911682099104,
      -0.011428390629589558,
      -0.004210263956338167,
      -0.0030674247536808252,
      -0.038506604731082916,
      -0.0006691378657706082,
      0.007113893982023001,
      -0.012813199311494827,
      0.03006374090909958,
      -0.003525304840877652,
      0.008681110106408596,
      -0.002183306496590376,
      0.008621548302471638,
      -0.011912329122424126,
      0.01897038333117962,
      0.01059452723711729,
      0.007765349466353655,
      -0.019297972321510315,
      -0.0005672316183336079,
      -0.02595398761332035,
      0.006280031055212021,
      -0.0051111336797475815,
      -0.0018659546039998531,
      0.024494726210832596,
      0.007326082326471806,
      -0.006693239789456129,
      0.004887777380645275,
      0.027130329981446266,
      0.0006435449467971921,
      0.004727705381810665,
      -0.012388821691274643,
      0.014808514155447483,
      -0.020563658326864243,
      0.0029389949049800634,
      -0.02403312362730503,
      0.004642085637897253,
      -0.009306507185101509,
      -0.005051571875810623,
      -0.014421363361179829,
      -0.008770451880991459,
      0.008755561895668507,
      0.0029818047769367695,
      -4.877191167906858e-05,
      -0.02495632879436016,
      -0.0009743912960402668,
      0.02465852163732052,
      -0.00945541076362133,
      -0.008621548302471638,
      -0.013021664693951607,
      -0.0059785000048577785,
      -0.03710690513253212,
      -0.0010804854100570083,
      -0.005922661162912846,
      0.0012386960443109274,
      0.003285197075456381,
      0.008055712096393108,
      0.0035811439156532288,
      -0.025462603196501732,
      0.006656013894826174,
      -4.5020227844361216e-05,
      -0.015165884047746658,
      0.009522417560219765,
      0.019431985914707184,
      -0.006864479742944241,
      0.009686212055385113,
      0.013148233294487,
      0.010103143751621246,
      0.002136773895472288,
      -0.0025127569679170847,
      0.006752801593393087,
      -0.017377110198140144,
      -0.020280739292502403,
      -0.019655343145132065,
      0.005602517165243626,
      -0.0012610317207872868,
      0.0001356423454126343,
      -0.02366086281836033,
      -0.013245020993053913,
      -0.023020576685667038,
      0.012381376698613167,
      0.014629828743636608,
      -0.01044562365859747,
      0.006555503699928522,
      0.0073000239208340645,
      0.0030972054228186607,
      0.002680273959413171,
      -0.01606675423681736,
      0.017928054556250572,
      0.018166301771998405,
      -0.015225445851683617,
      0.017049521207809448,
      0.026281576603651047,
      0.013706623576581478,
      0.027189891785383224,
      0.015962520614266396,
      -0.011569849215447903,
      0.009447965770959854,
      0.0017077440861612558,
      -0.015724273398518562,
      -0.04741106927394867,
      0.008011041209101677,
      -0.022231383249163628,
      0.0004862649948336184,
      0.010036136955022812,
      0.019863808527588844,
      0.003199577098712325,
      -0.0005220950697548687,
      0.017436672002077103,
      0.016096534207463264,
      0.019104396924376488,
      -0.0005960817798040807,
      0.01116036344319582,
      0.013818301260471344,
      -0.019848918542265892,
      0.005349380429834127,
      -0.0027156388387084007,
      0.017957836389541626,
      -0.008539650589227676,
      -0.006071565207093954,
      0.004973397124558687,
      -0.012433493509888649,
      -0.0044075618498027325,
      0.011592185124754906,
      -0.008405636996030807,
      -0.005286096129566431,
      -0.0056769694201648235,
      -0.007117616478353739,
      -0.006603897549211979,
      0.022499410435557365,
      0.0006844935705885291,
      0.010296719148755074,
      -0.004024133551865816,
      -0.005550400819629431,
      0.0025965154636651278,
      -0.01091467123478651,
      -0.04529663175344467,
      0.018866151571273804,
      -0.00031595592736266553,
      -0.027919521555304527,
      -0.0027268065605312586,
      -0.0007654601940885186,
      0.005066462326794863,
      0.0016621421091258526,
      0.009179938584566116,
      -0.009179938584566116,
      -0.005781202111393213,
      0.037077125161886215,
      0.0021665547974407673,
      0.0025257859379053116,
      0.017362220212817192,
      -0.007951479405164719,
      -0.003908732905983925,
      0.013654506765305996,
      -0.016885725781321526,
      0.011674082837998867,
      -0.0017030907329171896,
      -0.013728959485888481,
      0.002751003485172987,
      0.008524760603904724,
      0.06545824557542801,
      -0.009574534371495247,
      0.0034173494204878807,
      0.013185459189116955,
      -0.012850425206124783,
      0.032252632081508636,
      0.007221849635243416,
      0.011495397426187992,
      0.012604732997715473,
      0.028872506693005562,
      5.71768541703932e-05,
      0.012567507103085518,
      -0.004891499876976013,
      0.019491547718644142,
      -0.0007836078875698149,
      -0.014250123873353004,
      0.003000417957082391,
      -0.00015623298531863838,
      0.010006356053054333,
      0.010378616861999035
    ],
    "updated": "2023-10-01T00:00:00Z"
  }
]